mics_library/__init__.py
mics_library/country2ISO.py
mics_library/family_graph.py
mics_library/loaders.py
mics_library/preview.py
mics_library/processing.py
mics_library/recode.py
mics_library/swap_indicators.py
mics_library/utils.py
mics_library-1.0.1.dist-info/LICENSE
mics_library-1.0.1.dist-info/METADATA
mics_library-1.0.1.dist-info/PKG-INFO.sync-conflict-20211025-141409-OWU4YMD
mics_library-1.0.1.dist-info/PKG-INFO.sync-conflict-20211027-085915-OWU4YMD
mics_library-1.0.1.dist-info/SOURCES.sync-conflict-20211025-120425-OWU4YMD.txt
mics_library-1.0.1.dist-info/SOURCES.sync-conflict-20211027-085915-OWU4YMD.txt
mics_library-1.0.1.dist-info/WHEEL
mics_library-1.0.1.dist-info/top_level.txt
mics_library-1.0.1.dist-info/RECORD
