Metadata-Version: 2.1
Name: mics-library
Version: 1.0.1
Summary: A Python package to work with MICS data
Home-page: UNKNOWN
License: GPLv3
Platform: UNKNOWN
License-File: LICENSE
Requires-Dist: numpy
Requires-Dist: pandas
Requires-Dist: pyreadstat
